[{"__type__":"cc.SpriteFrame","content":{"name":"stage5","texture":"48ZINFwllNRZqDHa4UNqBs","rect":[244,158,53,101],"offset":[0,0],"originalSize":[53,101]}},[{"__type__":"cc.Prefab","_name":"stage5","data":{"__id__":1}},{"__type__":"cc.Node","_name":"stage5","_level":2,"_components":[{"__type__":"cc.Sprite","node":{"__id__":1},"_spriteFrame":{"__uuid__":"8f3RadFcBKcI4RBmFYTKeN"}}],"_prefab":{"__type__":"cc.PrefabInfo","root":{"__id__":1},"asset":{"__id__":0},"fileId":"9bCSJYtKxGrJhr2X72DEGF"},"_contentSize":{"__type__":"cc.Size","width":53,"height":101},"_anchorPoint":{"__type__":"cc.Vec2","x":0.5,"y":0.89},"_scale":{"__type__":"cc.Vec3","x":1,"y":1,"z":1}}]]